linear_model/__init__.py
linear_model_surya_sudhaharan-0.1.0.dist-info/licenses/LICENSE
linear_model_surya_sudhaharan-0.1.0.dist-info/METADATA
linear_model_surya_sudhaharan-0.1.0.dist-info/WHEEL
linear_model_surya_sudhaharan-0.1.0.dist-info/top_level.txt
linear_model_surya_sudhaharan-0.1.0.dist-info/RECORD
