Metadata-Version: 2.4
Name: linear_model_Surya_Sudhaharan
Version: 0.1.0
Summary: A lightweight Python library for Linear Regression with multiple training methods and regularization options.
Home-page: https://github.com/SuryaVsCode/Linear_Regression_Model
Author: Surya Sudhaharan
Author-email: surya.sudhaharan@gmail.com
License: MIT
Classifier: Development Status :: 3 - Alpha
Classifier: Intended Audience :: Developers
Classifier: Programming Language :: Python :: 3
Classifier: License :: OSI Approved :: MIT License
Classifier: Topic :: Scientific/Engineering :: Artificial Intelligence
Classifier: Topic :: Software Development :: Libraries :: Python Modules
Requires-Python: >=3.7
License-File: LICENSE
Requires-Dist: numpy>=1.20.0
Dynamic: author
Dynamic: author-email
Dynamic: classifier
Dynamic: description
Dynamic: description-content-type
Dynamic: home-page
Dynamic: license
Dynamic: license-file
Dynamic: requires-dist
Dynamic: requires-python
Dynamic: summary
